ByteAPI/Account.py
ByteAPI/ByteAPI.py
ByteAPI/ByteAPIClient.py
ByteAPI/Comment.py
ByteAPI/Community.py
ByteAPI/Conversation.py
ByteAPI/Post.py
ByteAPI/PublicProfile.py
ByteAPI/__init__.py
Byte.py-0.5.dist-info/METADATA
Byte.py-0.5.dist-info/WHEEL
Byte.py-0.5.dist-info/top_level.txt
Byte.py-0.5.dist-info/RECORD
