Metadata-Version: 2.1
Name: Byte.py
Version: 0.5
Summary: A Python API Wrapper to interact with with the SocialMedia platform Byte.co
Home-page: https://rpwnage.github.io/ByteAPI/
Author: rpwnage
Author-email: rpwnage@protonmail.com
License: MIT
Keywords: api,byte.co,byte
Platform: UNKNOWN
Requires-Dist: requests
